{
  "project_info": {
    "project_number": "740979013093",
    "project_id": "therichonline-database",
    "storage_bucket": "therichonline-database.appspot.com"
  },
  "client": [
    {
      "client_info": {
        "mobilesdk_app_id": "1:740979013093:android:510a7ecec3f0d531b22b0c",
        "android_client_info": {
          "package_name": "com.therichonline.therichonline"
        }
      },
      "oauth_client": [],
      "api_key": [
        {
          "current_key": "AIzaSyBnjDzCAXwNDmMfldB0lHHjVNLmHj16wFE"
        }
      ],
      "services": {
        "appinvite_service": {
          "other_platform_oauth_client": []
        }
      }
    }
  ],
  "configuration_version": "1"
}